{
  "input_datatypes": [],
  "output_datatype": "content_template_output",
  "input_groups": [
    {
      "name": "virtualmachine",
      "label": "Virtual Machine Input Variables"
    },
    {
      "name": "cloud",
      "label": "Cloud Input Variables"
    },
    {
      "name": "ssh_keys",
      "label": "SSH Keys"
    },
    {
      "name": "image_parameters",
      "label": "Image Parameters"
    }
  ],
  
  "output_groups": [
    {
      "name": "content_template_output",
      "label": "Outputs"
    }
  ],
  "template_input_params": [
    {
      "name": "ambiente",
      "type": "string",
      "description": "Seleciona ambiente",
      "hidden": false,
      "label": "Seleciona ambiente",
      "secured": false,
      "required": true,
      "immutable": false,
      "group_name": "virtualmachine",
      "options": [
        { "value": "dev-customer", "label": "dev-customer" },
        { "value": "th-customer", "label": "th-customer" },
        { "value": "th-company", "label": "th-company" },
        { "value": "ti-customer", "label": "ti-customer" },
        { "value": "ti-company", "label": "ti-company" },
        { "value": "tu-customer", "label": "tu-customer" },
        { "value": "tu-company", "label": "tu-company" },
        { "value": "prod-customer", "label": "prod-customer" },
        { "value": "prod-company", "label": "prod-company" },
        { "value": "ha-customer", "label": "ha-customer" },
        { "value": "ha-company", "label": "ha-company" },
        { "value": "prod-corp", "label": "prod-corp" },
        { "value": "ha-corp", "label": "ha-corp" },
        { "value": "structural", "label": "structural" }
      ]
    },
    {
      "name": "vm_1_name",
      "type": "string",
      "description": "Hostname of virtual machine",
      "default": "Hostname of virtual machine",
      "hidden": false,
      "label": "Hostname of virtual machine",
      "secured": false,
      "required": true,
      "immutable": false,
      "group_name": "virtualmachine"
    }
    
  ],
  "template_output_params": [
    {
      "name": "ip_address",
      "type": "string",
      "description": "IP gerado pelo IPAM",
      "hidden": false,
      "label": "IP gerado pelo IPAM",
      "secured": false,
      "group_name": "content_template_output"
    }
  ]
}
